{
  "_comment": "商业洞察-收入概览：接口索引说明。本页面已按模块拆分为多个接口，每个模块对应一个 `*-mock-for-backend.json`。后端对接时请按模块分别实现，避免一个大接口过重与字段耦合。",
  "endpoints": [
    {
      "name": "KPI 卡片",
      "suggestedMethod": "POST",
      "file": "revenue-overview-kpi-mock-for-backend.json"
    },
    {
      "name": "IAA 收入构成（表格 + 占比）",
      "suggestedMethod": "POST",
      "file": "revenue-overview-iaa-breakdown-mock-for-backend.json"
    },
    {
      "name": "IAP 收入分析（表格 + 订阅/一次性汇总）",
      "suggestedMethod": "POST",
      "file": "revenue-overview-iap-breakdown-mock-for-backend.json"
    },
    {
      "name": "近7天 IAA vs IAP 收入趋势",
      "suggestedMethod": "POST",
      "file": "revenue-overview-trend7d-mock-for-backend.json"
    },
    {
      "name": "ECPM 趋势（7天，预估 vs 真实）",
      "suggestedMethod": "POST",
      "file": "revenue-overview-ecpm7d-mock-for-backend.json"
    },
    {
      "name": "广告平台分布（饼图）",
      "suggestedMethod": "POST",
      "file": "revenue-overview-platform-pie-mock-for-backend.json"
    },
    {
      "name": "Top 国家收入",
      "suggestedMethod": "POST",
      "file": "revenue-overview-top-countries-mock-for-backend.json"
    },
    {
      "name": "AI 洞察建议",
      "suggestedMethod": "POST",
      "file": "revenue-overview-ai-insight-mock-for-backend.json"
    },
    {
      "name": "收入质量指标",
      "suggestedMethod": "POST",
      "file": "revenue-overview-quality-metrics-mock-for-backend.json"
    }
  ]
}
