{
  "_comment": "人员绩效对比 - 图表数据。包含 ROI 趋势、广告支出趋势、雷达图、利润对比。",
  "fieldDescription": {
    "request": {
      "startDate": { "type": "string", "required": true, "description": "开始日期，YYYY-MM-DD。" },
      "endDate": { "type": "string", "required": true, "description": "结束日期，YYYY-MM-DD。" },
      "staffIds": {
        "type": "string[]",
        "required": true,
        "description": "参与对比的人员 ID 列表。"
      }
    },
    "response": {
      "dates": { "type": "string[]", "required": true, "description": "横轴日期列表。" },
      "roiTrend": {
        "type": "ChartSeries[]",
        "required": true,
        "description": "首日 ROI 趋势序列。"
      },
      "adSpendTrend": {
        "type": "ChartSeries[]",
        "required": true,
        "description": "广告支出趋势序列。"
      },
      "radarSeries": { "type": "RadarSeries[]", "required": true, "description": "雷达图序列。" },
      "profitBars": { "type": "ProfitBar[]", "required": true, "description": "利润条形图数据。" }
    }
  },
  "sampleRequest": {
    "startDate": "2026-03-20",
    "endDate": "2026-03-26",
    "staffIds": ["zhang3", "li4", "wang5", "zhao6"]
  },
  "sampleResponse": {
    "dates": [
      "2026-03-20",
      "2026-03-21",
      "2026-03-22",
      "2026-03-23",
      "2026-03-24",
      "2026-03-25",
      "2026-03-26"
    ],
    "roiTrend": [{ "id": "zhao6", "name": "赵六", "values": [98, 99, 97, 95, 94, 98, 98] }],
    "adSpendTrend": [
      { "id": "zhao6", "name": "赵六", "values": [6800, 7200, 7600, 7100, 7400, 7800, 8100] }
    ],
    "radarSeries": [{ "id": "zhao6", "name": "赵六", "values": [28, 30, 20, 18, 96] }],
    "profitBars": [{ "id": "zhao6", "name": "赵六", "value": 15600 }]
  },
  "api": {
    "url": "POST /api/user-growth/performance-analysis/comparison-charts",
    "method": "POST",
    "priority": "P0",
    "requestBody": "startDate, endDate, staffIds",
    "responseBody": "dates, roiTrend, adSpendTrend, radarSeries, profitBars"
  }
}
